{"currentPage":1,"errorMessage":"","list":[{"country":"******","email":"duanmuci@alibaba-inc.com","enterpriseId":"2088101118131245","extSystem":"BUC","extUserId":"duanmuci","gmtCreate":1446446631000,"gmtModified":1446446631000,"id":1219,"imAccount":"端木赐","loginName":"duanmuci","mobileNum":"18600003437","nation":"汉族","nickName":"端木赐","phoneNum":"81119422","realName":"陈自强","securityId":746,"sex":"M","status":"NORMAL","type":"OPERATOR","uniqueId":"0000070876","workNo":"024001"},{"email":"qy1@alipay.com","enterpriseId":"2088101118131245","extSystem":"SELF","gmtCreate":1446444648000,"gmtModified":1446444648000,"id":1218,"loginName":"qy1@alipay.com","mobileNum":"18520035889","nickName":"qy1","realName":"qy","securityId":745,"status":"NORMAL","type":"OPERATOR","uniqueId":"0000070874"},{"email":"qy@alipay.com","enterpriseId":"2088101118131245","extSystem":"SELF","gmtCreate":1446444613000,"gmtModified":1446444699000,"id":1217,"loginName":"qy@alipay.com","mobileNum":"18520035889","nickName":"qy","realName":"qy","securityId":744,"status":"NORMAL","type":"PROOPERATOR","uniqueId":"0000070873"},{"country":"******","email":"huabiao.mahb@alibaba-inc.com","enterpriseId":"2088101118131245","extSystem":"BUC","extUserId":"huabiao.mahb","gmtCreate":1446434634000,"gmtModified":1446434634000,"id":1216,"imAccount":"城破","loginName":"huabiao.mahb","nation":"汉族","nickName":"城破","phoneNum":"81135119","realName":"马华标","securityId":743,"sex":"M","status":"NORMAL","type":"OPERATOR","uniqueId":"0000070872","workNo":"060984"},{"country":"******","email":"xiaoyang.hxy@alibaba-inc.com","enterpriseId":"2088101118131245","extSystem":"BUC","extUserId":"xiaoyang.hxy","gmtCreate":1446195872000,"gmtModified":1446195872000,"id":1215,"loginName":"xiaoyang.hxy","mobileNum":"18883862859","nation":"汉族","nickName":"讷语","phoneNum":"81671873","realName":"洪小洋","securityId":742,"sex":"M","status":"NORMAL","type":"OPERATOR","uniqueId":"0000070870","workNo":"085829"},{"email":"test11@alipay.com","enterpriseId":"2088101118131245","extSystem":"SELF","gmtCreate":1446123431000,"gmtModified":1446123431000,"id":1214,"loginName":"test11@alipay.com","mobileNum":"13065708660","nickName":"spencer","phoneNum":"0571-1","realName":"spencer","securityId":741,"status":"NORMAL","type":"OPERATOR","uniqueId":"0000070865"}],"pageSize":6,"startIndex":0,"success":true,"totalSize":565}
